{"1":{"objects":[],"backgroundImage":{"type":"image","version":"3.6.3","originX":"left","originY":"top","left":111,"top":-80,"width":598,"height":842,"fill":"rgb(0,0,0)","stroke":null,"strokeWidth":0,"strokeDashArray":null,"strokeLineCap":"butt","strokeDashOffset":0,"strokeLineJoin":"miter","strokeMiterLimit":4,"scaleX":1,"scaleY":1,"angle":0,"flipX":false,"flipY":false,"opacity":1,"shadow":null,"visible":true,"clipTo":null,"backgroundColor":"","fillRule":"nonzero","paintFirst":"fill","globalCompositeOperation":"source-over","transformMatrix":null,"skewX":0,"skewY":0,"crossOrigin":"","cropX":0,"cropY":0,"padding":0,"evented":true,"filters":[]}},"5":{"objects":[{"type":"nativeVideo","version":"3.6.3","originX":"left","originY":"top","left":159.38,"top":78.03,"width":246,"height":197,"fill":"rgba(0,0,0,0)","stroke":null,"strokeWidth":1,"strokeDashArray":null,"strokeLineCap":"butt","strokeDashOffset":0,"strokeLineJoin":"miter","strokeMiterLimit":4,"scaleX":1.71,"scaleY":1.22,"angle":0,"flipX":false,"flipY":false,"opacity":1,"shadow":null,"visible":true,"clipTo":null,"backgroundColor":"","fillRule":"nonzero","paintFirst":"fill","globalCompositeOperation":"source-over","transformMatrix":null,"skewX":0,"skewY":0,"rx":0,"ry":0,"id":"5e3e7d54-2d2a-4e47-b09d-7e0c1df70ea1","padding":0,"src":"./files/pageObject/video/1642021956647.mp4","evented":true,"videoId":"5e3e7d54-2d2a-4e47-b09d-7e0c1df70ea11642021956768video"},{"type":"nativeVideo","version":"3.6.3","originX":"left","originY":"top","left":163.08,"top":401.5,"width":246,"height":197,"fill":"rgba(0,0,0,0)","stroke":null,"strokeWidth":1,"strokeDashArray":null,"strokeLineCap":"butt","strokeDashOffset":0,"strokeLineJoin":"miter","strokeMiterLimit":4,"scaleX":1.7,"scaleY":1.18,"angle":0,"flipX":false,"flipY":false,"opacity":1,"shadow":null,"visible":true,"clipTo":null,"backgroundColor":"","fillRule":"nonzero","paintFirst":"fill","globalCompositeOperation":"source-over","transformMatrix":null,"skewX":0,"skewY":0,"rx":0,"ry":0,"id":"026f8605-0395-4362-9ed3-13994b23d1b0","padding":0,"src":"./files/pageObject/video/1642022025984.mp4","evented":true,"videoId":"026f8605-0395-4362-9ed3-13994b23d1b01642022026500video"}],"backgroundImage":{"type":"image","version":"3.6.3","originX":"left","originY":"top","left":111,"top":-80,"width":598,"height":842,"fill":"rgb(0,0,0)","stroke":null,"strokeWidth":0,"strokeDashArray":null,"strokeLineCap":"butt","strokeDashOffset":0,"strokeLineJoin":"miter","strokeMiterLimit":4,"scaleX":1,"scaleY":1,"angle":0,"flipX":false,"flipY":false,"opacity":1,"shadow":null,"visible":true,"clipTo":null,"backgroundColor":"","fillRule":"nonzero","paintFirst":"fill","globalCompositeOperation":"source-over","transformMatrix":null,"skewX":0,"skewY":0,"crossOrigin":"","cropX":0,"cropY":0,"padding":0,"evented":true,"filters":[]}}}